{
    "title": "台湾青年大陆互联网＋梦想之旅",
    "pos": "新华网>台湾频道>专访专题>台湾青年大陆互联网梦想之旅",
    "url": "http://www.xinhuanet.com/tw/zhuanti/twqndlmxzl/index.htm",
    "isFreeMod": true,
    "台湾青年大陆互联网＋梦想之旅1": {
        "list": {
            "大图（要闻左侧的）": {
                "nid": "11161095",
                "cid": "11160643"
            },
            "要闻": {
                "nid": "11161097",
                "cid": "11160645"
            },
            "实习活动": {
                "nid": "11161098",
                "cid": "11160646"
            },
            "参访活动": {
                "nid": "11161106",
                "cid": "11160654"
            },
            "亮点扫描": {
                "nid": "11161099",
                "cid": "11160647"
            },
            "参访企业巡礼": {
                "nid": "11161100",
                "cid": "11160648"
            },
            "精彩瞬间": {
                "nid": "11161103",
                "cid": "11160651"
            },
            "两岸青年交流": {
                "nid": "11161104",
                "cid": "11160652"
            }
        }
    }
}